{
  "slices": {
    "components": {
      "hero_side_by_side": {
        "library": "slices",
        "id": "hero_side_by_side",
        "name": "HeroSideBySide",
        "description": "HeroSideBySide",
        "model": {
          "id": "hero_side_by_side",
          "type": "SharedSlice",
          "name": "HeroSideBySide",
          "description": "HeroSideBySide",
          "variations": [
            {
              "id": "default",
              "name": "Default",
              "docURL": "...",
              "version": "sktwi1xtmkfgx8626",
              "description": "HeroSideBySide",
              "primary": {
                "title": {
                  "type": "StructuredText",
                  "config": {
                    "single": "heading1",
                    "label": "Title",
                    "placeholder": "This is where it all begins..."
                  }
                },
                "description": {
                  "type": "StructuredText",
                  "config": {
                    "single": "paragraph",
                    "label": "Description",
                    "placeholder": "A nice description of your feature"
                  }
                }
              },
              "items": {},
              "imageUrl": "https://images.prismic.io/slice-machine/621a5ec4-0387-4bc5-9860-2dd46cbc07cd_default_ss.png?auto=compress,format"
            }
          ]
        },
        "mocks": {
          "default": {
            "variation": "default",
            "name": "Default",
            "slice_type": "hero_side_by_side",
            "items": [],
            "primary": {
              "title": [
                {
                  "type": "heading1",
                  "text": "Reintermediate cross-media applications",
                  "spans": []
                }
              ],
              "description": [
                {
                  "type": "paragraph",
                  "text": "Tempor dolor laborum eiusmod nisi culpa dolore dolore. Officia incididunt enim ex velit tempor Lorem et duis qui consequat. Sint qui voluptate deserunt consectetur irure laborum adipisicing.",
                  "spans": []
                }
              ]
            }
          }
        },
        "meta": {
          "fileName": "index",
          "extension": "js"
        },
        "screenshotPaths": {}
      }
    }
  }
}